[{"acceleration":0.0,"curvature":0,"pose":{"rotation":{"radians":3.141592653589793},"translation":{"x":5.0,"y":3.0}},"time":0.0,"velocity":0,"position":0.0,"holonomicRotation":180.0,"angularVelocity":0.0,"angularAcceleration":0.0,"curveRadius":0.0},{"acceleration":0.5,"curvature":0,"pose":{"rotation":{"radians":3.141592653589793},"translation":{"x":4.9879761920000005,"y":3.0}},"time":0.15507293767772293,"velocity":0.07753646883886146,"position":0.01202380799999947,"holonomicRotation":179.64,"angularVelocity":0.0,"angularAcceleration":0.0,"curveRadius":0.0},{"acceleration":1.703107584011499,"curvature":0,"pose":{"rotation":{"radians":3.141592653589793},"translation":{"x":4.975905536,"y":3.0}},"time":0.21951976676372464,"velocity":0.18729635222072386,"position":0.024094464000000038,"holonomicRotation":179.28,"angularVelocity":0.0,"angularAcceleration":0.0,"curveRadius":0.0},{"acceleration":1.149758513922026,"curvature":0,"pose":{"rotation":{"radians":3.141592653589793},"translation":{"x":4.963789184,"y":3.0}},"time":0.26911267528676397,"velocity":0.24431622102524453,"position":0.036210815999999646,"holonomicRotation":178.92,"angularVelocity":0.0,"angularAcceleration":0.0,"curveRadius":0.0},{"acceleration":1.0914708634759884,"curvature":0,"pose":{"rotation":{"radians":3.141592653589793},"translation":{"x":4.951628288,"y":3.0}},"time":0.31103604935762597,"velocity":0.29007436232219513,"position":0.04837171199999979,"holonomicRotation":178.56,"angularVelocity":0.0,"angularAcceleration":0.0,"curveRadius":0.0},{"acceleration":1.0660286328081305,"curvature":0,"pose":{"rotation":{"radians":3.141592653589793},"translation":{"x":4.939424000000001,"y":3.0}},"time":0.3480689586849114,"velocity":0.3295525040212687,"position":0.0605759999999993,"holonomicRotation":178.2,"angularVelocity":0.0,"angularAcceleration":0.0,"curveRadius":0.0},{"acceleration":1.0516471688597577,"curvature":0,"pose":{"rotation":{"radians":3.141592653589793},"translation":{"x":4.9271774719999994,"y":3.0}},"time":0.3816347154020465,"velocity":0.36485183704347923,"position":0.07282252800000055,"holonomicRotation":177.84,"angularVelocity":0.0,"angularAcceleration":0.0,"curveRadius":0.0},{"acceleration":1.0423822214128287,"curvature":0,"pose":{"rotation":{"radians":3.141592653589793},"translation":{"x":4.914889856,"y":3.0}},"time":0.41257761451634695,"velocity":0.39710616495919676,"position":0.08511014399999972,"holonomicRotation":177.48,"angularVelocity":0.0,"angularAcceleration":0.0,"curveRadius":0.0},{"acceleration":1.0359132803065791,"curvature":0,"pose":{"rotation":{"radians":3.141592653589793},"translation":{"x":4.902562304,"y":3.0}},"time":0.441446929992723,"velocity":0.427012272254535,"position":0.09743769600000007,"holonomicRotation":177.12,"angularVelocity":0.0,"angularAcceleration":0.0,"curveRadius":0.0},{"acceleration":1.031141819011525,"curvature":0,"pose":{"rotation":{"radians":3.141592653589793},"translation":{"x":4.8901959680000004,"y":3.0}},"time":0.4686235845537429,"velocity":0.4550352572732329,"position":0.10980403199999955,"holonomicRotation":176.76,"angularVelocity":0.0,"angularAcceleration":0.0,"curveRadius":0.0},{"acceleration":1.0274791325500743,"curvature":0,"pose":{"rotation":{"radians":3.141592653589793},"translation":{"x":4.877792,"y":3.0}},"time":0.49438446577537126,"velocity":0.4815040251645571,"position":0.12220799999999965,"holonomicRotation":176.4,"angularVelocity":0.0,"angularAcceleration":0.0,"curveRadius":0.0},{"acceleration":1.0245809041497476,"curvature":0,"pose":{"rotation":{"radians":3.141592653589793},"translation":{"x":4.865351552000001,"y":3.0}},"time":0.5189382390997972,"velocity":0.5066613524375854,"position":0.1346484479999992,"holonomicRotation":176.04,"angularVelocity":0.0,"angularAcceleration":0.0,"curveRadius":0.0},{"acceleration":1.022232159854021,"curvature":0,"pose":{"rotation":{"radians":3.141592653589793},"translation":{"x":4.852875775999999,"y":3.0}},"time":0.5424467236512734,"velocity":0.5306924813755358,"position":0.14712422400000058,"holonomicRotation":175.68,"angularVelocity":0.0,"angularAcceleration":0.0,"curveRadius":0.0},{"acceleration":1.0202916857228537,"curvature":0,"pose":{"rotation":{"radians":3.141592653589793},"translation":{"x":4.840365824,"y":3.0}},"time":0.5650383632993425,"velocity":0.5537425434753075,"position":0.15963417599999996,"holonomicRotation":175.32,"angularVelocity":0.0,"angularAcceleration":0.0,"curveRadius":0.0},{"acceleration":1.0186628647801035,"curvature":0,"pose":{"rotation":{"radians":3.141592653589793},"translation":{"x":4.827822848,"y":3.0}},"time":0.5868170958654829,"velocity":0.5759277295824118,"position":0.17217715199999972,"holonomicRotation":174.96,"angularVelocity":0.0,"angularAcceleration":0.0,"curveRadius":0.0},{"acceleration":1.0172773472780046,"curvature":0,"pose":{"rotation":{"radians":3.141592653589793},"translation":{"x":4.815248,"y":3.0}},"time":0.6078684068118684,"velocity":0.5973427513386752,"position":0.18475199999999958,"holonomicRotation":174.6,"angularVelocity":0.0,"angularAcceleration":0.0,"curveRadius":0.0},{"acceleration":1.0160854114914493,"curvature":0,"pose":{"rotation":{"radians":3.141592653589793},"translation":{"x":4.802642432,"y":3.0}},"time":0.6282635879947207,"velocity":0.6180659974032964,"position":0.19735756800000015,"holonomicRotation":174.24,"angularVelocity":0.0,"angularAcceleration":0.0,"curveRadius":0.0},{"acceleration":1.0150500194786705,"curvature":0,"pose":{"rotation":{"radians":3.141592653589793},"translation":{"x":4.790007296,"y":3.0}},"time":0.6480628117705879,"velocity":0.6381631998826529,"position":0.20999270400000025,"holonomicRotation":173.88,"angularVelocity":0.0,"angularAcceleration":0.0,"curveRadius":0.0},{"acceleration":1.0141430137079714,"curvature":0,"pose":{"rotation":{"radians":3.141592653589793},"translation":{"x":4.7773437439999995,"y":3.0}},"time":0.6673173997431814,"velocity":0.6576901057568841,"position":0.2226562560000005,"holonomicRotation":173.52,"angularVelocity":0.0,"angularAcceleration":0.0,"curveRadius":0.0},{"acceleration":1.0133426054912644,"curvature":0,"pose":{"rotation":{"radians":3.141592653589793},"translation":{"x":4.764652928,"y":3.0}},"time":0.6860715297984601,"velocity":0.6766944647708223,"position":0.2353470719999997,"holonomicRotation":173.16,"angularVelocity":0.0,"angularAcceleration":0.0,"curveRadius":0.0},{"acceleration":1.012631670542904,"curvature":0,"pose":{"rotation":{"radians":3.141592653589793},"translation":{"x":4.751936,"y":3.0}},"time":0.7043635424977648,"velocity":0.6952175361481112,"position":0.24806400000000028,"holonomicRotation":172.79999999999998,"angularVelocity":0.0,"angularAcceleration":0.0,"curveRadius":0.0},{"acceleration":1.0119965643156053,"curvature":0,"pose":{"rotation":{"radians":3.141592653589793},"translation":{"x":4.739194112000001,"y":3.0}},"time":0.7222269560186731,"velocity":0.7132952492582194,"position":0.26080588799999926,"holonomicRotation":172.44,"angularVelocity":0.0,"angularAcceleration":0.0,"curveRadius":0.0},{"acceleration":1.0114262810587413,"curvature":0,"pose":{"rotation":{"radians":3.141592653589793},"translation":{"x":4.726428415999999,"y":3.0}},"time":0.7396912653262857,"velocity":0.7309591106724775,"position":0.2735715840000008,"holonomicRotation":172.07999999999998,"angularVelocity":0.0,"angularAcceleration":0.0,"curveRadius":0.0},{"acceleration":1.0109118455896247,"curvature":0,"pose":{"rotation":{"radians":3.141592653589793},"translation":{"x":4.713640064000001,"y":3.0}},"time":0.7567825790806754,"velocity":0.7482369222034789,"position":0.2863599359999993,"holonomicRotation":171.72,"angularVelocity":0.0,"angularAcceleration":0.0,"curveRadius":0.0},{"acceleration":1.0104458659201783,"curvature":0,"pose":{"rotation":{"radians":3.141592653589793},"translation":{"x":4.700830207999999,"y":3.0}},"time":0.7735241327844927,"velocity":0.7651533559325818,"position":0.2991697920000007,"holonomicRotation":171.35999999999999,"angularVelocity":0.0,"angularAcceleration":0.0,"curveRadius":0.0},{"acceleration":1.0100221992071674,"curvature":0,"pose":{"rotation":{"radians":3.141592653589793},"translation":{"x":4.688,"y":3.0}},"time":0.7899367063252604,"velocity":0.7817304195548773,"position":0.3120000000000003,"holonomicRotation":171.0,"angularVelocity":0.0,"angularAcceleration":0.0,"curveRadius":0.0},{"acceleration":1.009635698867175,"curvature":0,"pose":{"rotation":{"radians":3.141592653589793},"translation":{"x":4.675150592,"y":3.0}},"time":0.8060389667999934,"velocity":0.7979878365626257,"position":0.3248494080000004,"holonomicRotation":170.64,"angularVelocity":0.0,"angularAcceleration":0.0,"curveRadius":0.0},{"acceleration":1.0092820207565165,"curvature":0,"pose":{"rotation":{"radians":3.141592653589793},"translation":{"x":4.662283136,"y":3.0}},"time":0.8218477523239933,"velocity":0.8139433595619947,"position":0.3377168639999999,"holonomicRotation":170.28,"angularVelocity":0.0,"angularAcceleration":0.0,"curveRadius":0.0},{"acceleration":1.0089574729033026,"curvature":0,"pose":{"rotation":{"radians":3.141592653589793},"translation":{"x":4.649398784,"y":3.0}},"time":0.8373783087708928,"velocity":0.8296130305474405,"position":0.35060121600000027,"holonomicRotation":169.92,"angularVelocity":0.0,"angularAcceleration":0.0,"curveRadius":0.0},{"acceleration":1.008658897803328,"curvature":0,"pose":{"rotation":{"radians":3.141592653589793},"translation":{"x":4.636498688,"y":3.0}},"time":0.8526444886352113,"velocity":0.8450113987030513,"position":0.36350131200000035,"holonomicRotation":169.56,"angularVelocity":0.0,"angularAcceleration":0.0,"curveRadius":0.0},{"acceleration":1.0083835793135771,"curvature":0,"pose":{"rotation":{"radians":3.141592653589793},"translation":{"x":4.623583999999999,"y":3.0}},"time":0.8676589191612114,"velocity":0.8601517038982144,"position":0.37641600000000075,"holonomicRotation":169.2,"angularVelocity":0.0,"angularAcceleration":0.0,"curveRadius":0.0},{"acceleration":1.0081291683643272,"curvature":0,"pose":{"rotation":{"radians":3.141592653589793},"translation":{"x":4.610655872,"y":3.0}},"time":0.8824331453430343,"velocity":0.875046032252122,"position":0.3893441280000003,"holonomicRotation":168.84,"angularVelocity":0.0,"angularAcceleration":0.0,"curveRadius":0.0},{"acceleration":1.007893623187791,"curvature":0,"pose":{"rotation":{"radians":3.141592653589793},"translation":{"x":4.5977154559999995,"y":3.0}},"time":0.8969777522324626,"velocity":0.8897054487877499,"position":0.40228454400000047,"holonomicRotation":168.48,"angularVelocity":0.0,"angularAcceleration":0.0,"curveRadius":0.0},{"acceleration":1.007675160854845,"curvature":0,"pose":{"rotation":{"radians":3.141592653589793},"translation":{"x":4.584763904000001,"y":3.0}},"time":0.9113024700943142,"velocity":0.9041401111633915,"position":0.4152360959999992,"holonomicRotation":168.12,"angularVelocity":0.0,"angularAcceleration":0.0,"curveRadius":0.0},{"acceleration":1.0074722177111552,"curvature":0,"pose":{"rotation":{"radians":3.141592653589793},"translation":{"x":4.571802367999999,"y":3.0}},"time":0.9254162652558044,"velocity":0.9183593676750591,"position":0.4281976320000007,"holonomicRotation":167.76,"angularVelocity":0.0,"angularAcceleration":0.0,"curveRadius":0.0},{"acceleration":1.007283416854975,"curvature":0,"pose":{"rotation":{"radians":3.141592653589793},"translation":{"x":4.558832000000001,"y":3.0}},"time":0.9393274189546469,"velocity":0.9323718421052238,"position":0.44116799999999934,"holonomicRotation":167.39999999999998,"angularVelocity":0.0,"angularAcceleration":0.0,"curveRadius":0.0},{"acceleration":1.0071075412338653,"curvature":0,"pose":{"rotation":{"radians":3.141592653589793},"translation":{"x":4.545853952,"y":3.0}},"time":0.9530435960647342,"velocity":0.9461855075096921,"position":0.45414604800000014,"holonomicRotation":167.04,"angularVelocity":0.0,"angularAcceleration":0.0,"curveRadius":0.0},{"acceleration":1.006943511270176,"curvature":0,"pose":{"rotation":{"radians":3.141592653589793},"translation":{"x":4.532869376,"y":3.0}},"time":0.9665719052403707,"velocity":0.9598077506525561,"position":0.46713062400000016,"holonomicRotation":166.67999999999998,"angularVelocity":0.0,"angularAcceleration":0.0,"curveRadius":0.0},{"acceleration":1.0067903661407127,"curvature":0,"pose":{"rotation":{"radians":3.141592653589793},"translation":{"x":4.519879424,"y":3.0}},"time":0.9799189517506026,"velocity":0.9732454284954896,"position":0.480120576,"holonomicRotation":166.32,"angularVelocity":0.0,"angularAcceleration":0.0,"curveRadius":0.0},{"acceleration":1.0066472480378557,"curvature":0,"pose":{"rotation":{"radians":3.141592653589793},"translation":{"x":4.506885248,"y":3.0}},"time":0.9930908840584534,"velocity":0.9865049179045284,"position":0.4931147520000003,"holonomicRotation":165.95999999999998,"angularVelocity":0.0,"angularAcceleration":0.0,"curveRadius":0.0},{"acceleration":0.7698428584313045,"curvature":0,"pose":{"rotation":{"radians":3.141592653589793},"translation":{"x":4.493887999999999,"y":3.0}},"time":1.0061331874515977,"velocity":0.996545442029235,"position":0.5061120000000008,"holonomicRotation":165.6,"angularVelocity":0.0,"angularAcceleration":0.0,"curveRadius":0.0},{"acceleration":0.2657522366635418,"curvature":0,"pose":{"rotation":{"radians":3.141592653589793},"translation":{"x":4.480888832,"y":3.0}},"time":1.0191323554515972,"velocity":1.0,"position":0.5191111680000002,"holonomicRotation":165.23999999999998,"angularVelocity":0.0,"angularAcceleration":0.0,"curveRadius":0.0},{"acceleration":0.0,"curvature":0,"pose":{"rotation":{"radians":3.141592653589793},"translation":{"x":4.467888896,"y":3.0}},"time":1.0321322914515971,"velocity":1.0,"position":0.5321111040000002,"holonomicRotation":164.88,"angularVelocity":0.0,"angularAcceleration":0.0,"curveRadius":0.0},{"acceleration":0.0,"curvature":0,"pose":{"rotation":{"radians":3.141592653589793},"translation":{"x":4.454889344,"y":3.0}},"time":1.0451318434515973,"velocity":1.0,"position":0.5451106560000003,"holonomicRotation":164.51999999999998,"angularVelocity":0.0,"angularAcceleration":0.0,"curveRadius":0.0},{"acceleration":0.0,"curvature":0,"pose":{"rotation":{"radians":3.141592653589793},"translation":{"x":4.441891328,"y":3.0}},"time":1.0581298594515973,"velocity":1.0,"position":0.5581086720000004,"holonomicRotation":164.16,"angularVelocity":0.0,"angularAcceleration":0.0,"curveRadius":0.0},{"acceleration":0.0,"curvature":0,"pose":{"rotation":{"radians":3.141592653589793},"translation":{"x":4.428896,"y":3.0}},"time":1.071125187451597,"velocity":1.0,"position":0.5711040000000001,"holonomicRotation":163.79999999999998,"angularVelocity":0.0,"angularAcceleration":0.0,"curveRadius":0.0},{"acceleration":0.0,"curvature":0,"pose":{"rotation":{"radians":3.141592653589793},"translation":{"x":4.415904511999999,"y":3.0}},"time":1.0841166754515978,"velocity":1.0,"position":0.5840954880000009,"holonomicRotation":163.44,"angularVelocity":0.0,"angularAcceleration":0.0,"curveRadius":0.0},{"acceleration":0.0,"curvature":0,"pose":{"rotation":{"radians":3.141592653589793},"translation":{"x":4.402918016,"y":3.0}},"time":1.0971031714515969,"velocity":1.0,"position":0.5970819839999999,"holonomicRotation":163.07999999999998,"angularVelocity":0.0,"angularAcceleration":0.0,"curveRadius":0.0},{"acceleration":0.0,"curvature":0,"pose":{"rotation":{"radians":3.141592653589793},"translation":{"x":4.389937664,"y":3.0}},"time":1.1100835234515973,"velocity":1.0,"position":0.6100623360000004,"holonomicRotation":162.72,"angularVelocity":0.0,"angularAcceleration":0.0,"curveRadius":0.0},{"acceleration":0.0,"curvature":0,"pose":{"rotation":{"radians":3.141592653589793},"translation":{"x":4.376964608,"y":3.0}},"time":1.1230565794515972,"velocity":1.0,"position":0.6230353920000002,"holonomicRotation":162.35999999999999,"angularVelocity":0.0,"angularAcceleration":0.0,"curveRadius":0.0},{"acceleration":0.0,"curvature":0,"pose":{"rotation":{"radians":3.141592653589793},"translation":{"x":4.364,"y":3.0}},"time":1.136021187451597,"velocity":1.0,"position":0.6360000000000001,"holonomicRotation":162.0,"angularVelocity":0.0,"angularAcceleration":0.0,"curveRadius":0.0},{"acceleration":0.0,"curvature":0,"pose":{"rotation":{"radians":3.141592653589793},"translation":{"x":4.351044991999999,"y":3.0}},"time":1.1489761954515976,"velocity":1.0,"position":0.6489550080000006,"holonomicRotation":161.64,"angularVelocity":0.0,"angularAcceleration":0.0,"curveRadius":0.0},{"acceleration":0.0,"curvature":0,"pose":{"rotation":{"radians":3.141592653589793},"translation":{"x":4.3381007359999995,"y":3.0}},"time":1.1619204514515975,"velocity":1.0,"position":0.6618992640000005,"holonomicRotation":161.27999999999997,"angularVelocity":0.0,"angularAcceleration":0.0,"curveRadius":0.0},{"acceleration":0.0,"curvature":0,"pose":{"rotation":{"radians":3.141592653589793},"translation":{"x":4.3251683839999995,"y":3.0}},"time":1.1748528034515975,"velocity":1.0,"position":0.6748316160000005,"holonomicRotation":160.92,"angularVelocity":0.0,"angularAcceleration":0.0,"curveRadius":0.0},{"acceleration":0.0,"curvature":0,"pose":{"rotation":{"radians":3.141592653589793},"translation":{"x":4.312249088,"y":3.0}},"time":1.1877720994515972,"velocity":1.0,"position":0.6877509120000003,"holonomicRotation":160.55999999999997,"angularVelocity":0.0,"angularAcceleration":0.0,"curveRadius":0.0},{"acceleration":0.0,"curvature":0,"pose":{"rotation":{"radians":3.141592653589793},"translation":{"x":4.299344,"y":3.0}},"time":1.2006771874515973,"velocity":1.0,"position":0.7006560000000004,"holonomicRotation":160.2,"angularVelocity":0.0,"angularAcceleration":0.0,"curveRadius":0.0},{"acceleration":0.0,"curvature":0,"pose":{"rotation":{"radians":3.141592653589793},"translation":{"x":4.286454271999999,"y":3.0}},"time":1.2135669154515976,"velocity":1.0,"position":0.7135457280000006,"holonomicRotation":159.83999999999997,"angularVelocity":0.0,"angularAcceleration":0.0,"curveRadius":0.0},{"acceleration":0.0,"curvature":0,"pose":{"rotation":{"radians":3.141592653589793},"translation":{"x":4.273581055999999,"y":3.0}},"time":1.2264401314515976,"velocity":1.0,"position":0.7264189440000006,"holonomicRotation":159.48,"angularVelocity":0.0,"angularAcceleration":0.0,"curveRadius":0.0},{"acceleration":0.0,"curvature":0,"pose":{"rotation":{"radians":3.141592653589793},"translation":{"x":4.260725503999999,"y":3.0}},"time":1.239295683451598,"velocity":1.0,"position":0.7392744960000011,"holonomicRotation":159.11999999999998,"angularVelocity":0.0,"angularAcceleration":0.0,"curveRadius":0.0},{"acceleration":0.0,"curvature":0,"pose":{"rotation":{"radians":3.141592653589793},"translation":{"x":4.247888767999999,"y":3.0}},"time":1.2521324194515977,"velocity":1.0,"position":0.7521112320000007,"holonomicRotation":158.76,"angularVelocity":0.0,"angularAcceleration":0.0,"curveRadius":0.0},{"acceleration":0.0,"curvature":0,"pose":{"rotation":{"radians":3.141592653589793},"translation":{"x":4.235071999999999,"y":3.0}},"time":1.2649491874515981,"velocity":1.0,"position":0.7649280000000012,"holonomicRotation":158.39999999999998,"angularVelocity":0.0,"angularAcceleration":0.0,"curveRadius":0.0},{"acceleration":0.0,"curvature":0,"pose":{"rotation":{"radians":3.141592653589793},"translation":{"x":4.222276352,"y":3.0}},"time":1.2777448354515972,"velocity":1.0,"position":0.7777236480000003,"holonomicRotation":158.04,"angularVelocity":0.0,"angularAcceleration":0.0,"curveRadius":0.0},{"acceleration":0.0,"curvature":0,"pose":{"rotation":{"radians":3.141592653589793},"translation":{"x":4.209502976,"y":3.0}},"time":1.2905182114515974,"velocity":1.0,"position":0.7904970240000004,"holonomicRotation":157.67999999999998,"angularVelocity":0.0,"angularAcceleration":0.0,"curveRadius":0.0},{"acceleration":0.0,"curvature":0,"pose":{"rotation":{"radians":3.141592653589793},"translation":{"x":4.1967530239999995,"y":3.0}},"time":1.3032681634515975,"velocity":1.0,"position":0.8032469760000005,"holonomicRotation":157.32,"angularVelocity":0.0,"angularAcceleration":0.0,"curveRadius":0.0},{"acceleration":0.0,"curvature":0,"pose":{"rotation":{"radians":3.141592653589793},"translation":{"x":4.184027648,"y":3.0}},"time":1.3159935394515971,"velocity":1.0,"position":0.8159723520000002,"holonomicRotation":156.95999999999998,"angularVelocity":0.0,"angularAcceleration":0.0,"curveRadius":0.0},{"acceleration":0.0,"curvature":0,"pose":{"rotation":{"radians":3.141592653589793},"translation":{"x":4.171328,"y":3.0}},"time":1.328693187451597,"velocity":1.0,"position":0.8286720000000001,"holonomicRotation":156.6,"angularVelocity":0.0,"angularAcceleration":0.0,"curveRadius":0.0},{"acceleration":0.0,"curvature":0,"pose":{"rotation":{"radians":3.141592653589793},"translation":{"x":4.158655231999999,"y":3.0}},"time":1.3413659554515978,"velocity":1.0,"position":0.8413447680000008,"holonomicRotation":156.23999999999998,"angularVelocity":0.0,"angularAcceleration":0.0,"curveRadius":0.0},{"acceleration":0.0,"curvature":0,"pose":{"rotation":{"radians":3.141592653589793},"translation":{"x":4.146010496,"y":3.0}},"time":1.3540106914515972,"velocity":1.0,"position":0.8539895040000003,"holonomicRotation":155.88,"angularVelocity":0.0,"angularAcceleration":0.0,"curveRadius":0.0},{"acceleration":0.0,"curvature":0,"pose":{"rotation":{"radians":3.141592653589793},"translation":{"x":4.133394944,"y":3.0}},"time":1.366626243451597,"velocity":1.0,"position":0.866605056,"holonomicRotation":155.51999999999998,"angularVelocity":0.0,"angularAcceleration":0.0,"curveRadius":0.0},{"acceleration":0.0,"curvature":0,"pose":{"rotation":{"radians":3.141592653589793},"translation":{"x":4.120809728,"y":3.0}},"time":1.3792114594515967,"velocity":1.0,"position":0.8791902719999998,"holonomicRotation":155.15999999999997,"angularVelocity":0.0,"angularAcceleration":0.0,"curveRadius":0.0},{"acceleration":0.0,"curvature":0,"pose":{"rotation":{"radians":3.141592653589793},"translation":{"x":4.108255999999999,"y":3.0}},"time":1.391765187451598,"velocity":1.0,"position":0.891744000000001,"holonomicRotation":154.79999999999998,"angularVelocity":0.0,"angularAcceleration":0.0,"curveRadius":0.0},{"acceleration":0.0,"curvature":0,"pose":{"rotation":{"radians":3.141592653589793},"translation":{"x":4.095734911999999,"y":3.0}},"time":1.4042862754515977,"velocity":1.0,"position":0.9042650880000007,"holonomicRotation":154.44,"angularVelocity":0.0,"angularAcceleration":0.0,"curveRadius":0.0},{"acceleration":0.0,"curvature":0,"pose":{"rotation":{"radians":3.141592653589793},"translation":{"x":4.0832476159999995,"y":3.0}},"time":1.4167735714515974,"velocity":1.0,"position":0.9167523840000005,"holonomicRotation":154.07999999999998,"angularVelocity":0.0,"angularAcceleration":0.0,"curveRadius":0.0},{"acceleration":0.0,"curvature":0,"pose":{"rotation":{"radians":3.141592653589793},"translation":{"x":4.070795264,"y":3.0}},"time":1.429225923451597,"velocity":1.0,"position":0.929204736,"holonomicRotation":153.71999999999997,"angularVelocity":0.0,"angularAcceleration":0.0,"curveRadius":0.0},{"acceleration":0.0,"curvature":0,"pose":{"rotation":{"radians":3.141592653589793},"translation":{"x":4.058379007999999,"y":3.0}},"time":1.4416421794515977,"velocity":1.0,"position":0.9416209920000007,"holonomicRotation":153.35999999999999,"angularVelocity":0.0,"angularAcceleration":0.0,"curveRadius":0.0},{"acceleration":0.0,"curvature":0,"pose":{"rotation":{"radians":3.141592653589793},"translation":{"x":4.045999999999999,"y":3.0}},"time":1.4540211874515976,"velocity":1.0,"position":0.9540000000000006,"holonomicRotation":152.99999999999997,"angularVelocity":0.0,"angularAcceleration":0.0,"curveRadius":0.0},{"acceleration":0.0,"curvature":0,"pose":{"rotation":{"radians":3.141592653589793},"translation":{"x":4.033659392,"y":3.0}},"time":1.4663617954515973,"velocity":1.0,"position":0.9663406080000003,"holonomicRotation":152.64,"angularVelocity":0.0,"angularAcceleration":0.0,"curveRadius":0.0},{"acceleration":0.0,"curvature":0,"pose":{"rotation":{"radians":3.141592653589793},"translation":{"x":4.021358336,"y":3.0}},"time":1.4786628514515974,"velocity":1.0,"position":0.9786416640000004,"holonomicRotation":152.27999999999997,"angularVelocity":0.0,"angularAcceleration":0.0,"curveRadius":0.0},{"acceleration":0.0,"curvature":0,"pose":{"rotation":{"radians":3.141592653589793},"translation":{"x":4.009097983999999,"y":3.0}},"time":1.4909232034515976,"velocity":1.0,"position":0.9909020160000006,"holonomicRotation":151.92,"angularVelocity":0.0,"angularAcceleration":0.0,"curveRadius":0.0},{"acceleration":0.0,"curvature":0,"pose":{"rotation":{"radians":3.141592653589793},"translation":{"x":3.996879488,"y":3.0}},"time":1.5031416994515971,"velocity":1.0,"position":1.0031205120000002,"holonomicRotation":151.55999999999997,"angularVelocity":0.0,"angularAcceleration":0.0,"curveRadius":0.0},{"acceleration":0.0,"curvature":0,"pose":{"rotation":{"radians":3.141592653589793},"translation":{"x":3.9847039999999994,"y":3.0}},"time":1.5153171874515976,"velocity":1.0,"position":1.0152960000000006,"holonomicRotation":151.2,"angularVelocity":0.0,"angularAcceleration":0.0,"curveRadius":0.0},{"acceleration":0.0,"curvature":0,"pose":{"rotation":{"radians":3.141592653589793},"translation":{"x":3.9725726719999996,"y":3.0}},"time":1.5274485154515973,"velocity":1.0,"position":1.0274273280000004,"holonomicRotation":150.83999999999997,"angularVelocity":0.0,"angularAcceleration":0.0,"curveRadius":0.0},{"acceleration":0.0,"curvature":0,"pose":{"rotation":{"radians":3.141592653589793},"translation":{"x":3.9604866559999996,"y":3.0}},"time":1.5395345314515974,"velocity":1.0,"position":1.0395133440000004,"holonomicRotation":150.48,"angularVelocity":0.0,"angularAcceleration":0.0,"curveRadius":0.0},{"acceleration":0.0,"curvature":0,"pose":{"rotation":{"radians":3.141592653589793},"translation":{"x":3.9484471039999995,"y":3.0}},"time":1.5515740834515974,"velocity":1.0,"position":1.0515528960000005,"holonomicRotation":150.11999999999998,"angularVelocity":0.0,"angularAcceleration":0.0,"curveRadius":0.0},{"acceleration":0.0,"curvature":0,"pose":{"rotation":{"radians":3.141592653589793},"translation":{"x":3.9364551679999997,"y":3.0}},"time":1.5635660194515972,"velocity":1.0,"position":1.0635448320000003,"holonomicRotation":149.76,"angularVelocity":0.0,"angularAcceleration":0.0,"curveRadius":0.0},{"acceleration":0.0,"curvature":0,"pose":{"rotation":{"radians":3.141592653589793},"translation":{"x":3.9245119999999996,"y":3.0}},"time":1.5755091874515974,"velocity":1.0,"position":1.0754880000000004,"holonomicRotation":149.39999999999998,"angularVelocity":0.0,"angularAcceleration":0.0,"curveRadius":0.0},{"acceleration":0.0,"curvature":0,"pose":{"rotation":{"radians":3.141592653589793},"translation":{"x":3.9126187519999993,"y":3.0}},"time":1.5874024354515976,"velocity":1.0,"position":1.0873812480000007,"holonomicRotation":149.03999999999996,"angularVelocity":0.0,"angularAcceleration":0.0,"curveRadius":0.0},{"acceleration":0.0,"curvature":0,"pose":{"rotation":{"radians":3.141592653589793},"translation":{"x":3.9007765759999997,"y":3.0}},"time":1.5992446114515972,"velocity":1.0,"position":1.0992234240000003,"holonomicRotation":148.67999999999998,"angularVelocity":0.0,"angularAcceleration":0.0,"curveRadius":0.0},{"acceleration":0.0,"curvature":0,"pose":{"rotation":{"radians":3.141592653589793},"translation":{"x":3.8889866239999993,"y":3.0}},"time":1.6110345634515977,"velocity":1.0,"position":1.1110133760000007,"holonomicRotation":148.31999999999996,"angularVelocity":0.0,"angularAcceleration":0.0,"curveRadius":0.0},{"acceleration":0.0,"curvature":0,"pose":{"rotation":{"radians":3.141592653589793},"translation":{"x":3.8772500479999996,"y":3.0}},"time":1.6227711394515973,"velocity":1.0,"position":1.1227499520000004,"holonomicRotation":147.95999999999998,"angularVelocity":0.0,"angularAcceleration":0.0,"curveRadius":0.0},{"acceleration":0.0,"curvature":0,"pose":{"rotation":{"radians":3.141592653589793},"translation":{"x":3.8655679999999992,"y":3.0}},"time":1.6344531874515977,"velocity":1.0,"position":1.1344320000000008,"holonomicRotation":147.59999999999997,"angularVelocity":0.0,"angularAcceleration":0.0,"curveRadius":0.0},{"acceleration":0.0,"curvature":0,"pose":{"rotation":{"radians":3.141592653589793},"translation":{"x":3.8539416319999993,"y":3.0}},"time":1.6460795554515977,"velocity":1.0,"position":1.1460583680000007,"holonomicRotation":147.23999999999998,"angularVelocity":0.0,"angularAcceleration":0.0,"curveRadius":0.0},{"acceleration":0.0,"curvature":0,"pose":{"rotation":{"radians":3.141592653589793},"translation":{"x":3.842372095999999,"y":3.0}},"time":1.6576490914515978,"velocity":1.0,"position":1.1576279040000008,"holonomicRotation":146.87999999999997,"angularVelocity":0.0,"angularAcceleration":0.0,"curveRadius":0.0},{"acceleration":0.0,"curvature":0,"pose":{"rotation":{"radians":3.141592653589793},"translation":{"x":3.830860543999999,"y":3.0}},"time":1.6691606434515978,"velocity":1.0,"position":1.1691394560000008,"holonomicRotation":146.51999999999998,"angularVelocity":0.0,"angularAcceleration":0.0,"curveRadius":0.0},{"acceleration":0.0,"curvature":0,"pose":{"rotation":{"radians":3.141592653589793},"translation":{"x":3.819408127999999,"y":3.0}},"time":1.6806130594515978,"velocity":1.0,"position":1.1805918720000008,"holonomicRotation":146.15999999999997,"angularVelocity":0.0,"angularAcceleration":0.0,"curveRadius":0.0},{"acceleration":0.0,"curvature":0,"pose":{"rotation":{"radians":3.141592653589793},"translation":{"x":3.8080159999999994,"y":3.0}},"time":1.6920051874515976,"velocity":1.0,"position":1.1919840000000006,"holonomicRotation":145.79999999999998,"angularVelocity":0.0,"angularAcceleration":0.0,"curveRadius":0.0},{"acceleration":0.0,"curvature":0,"pose":{"rotation":{"radians":3.141592653589793},"translation":{"x":3.7966853119999993,"y":3.0}},"time":1.7033358754515977,"velocity":1.0,"position":1.2033146880000007,"holonomicRotation":145.43999999999997,"angularVelocity":0.0,"angularAcceleration":0.0,"curveRadius":0.0},{"acceleration":0.0,"curvature":0,"pose":{"rotation":{"radians":3.141592653589793},"translation":{"x":3.785417215999999,"y":3.0}},"time":1.714603971451598,"velocity":1.0,"position":1.214582784000001,"holonomicRotation":145.07999999999998,"angularVelocity":0.0,"angularAcceleration":0.0,"curveRadius":0.0},{"acceleration":0.0,"curvature":0,"pose":{"rotation":{"radians":3.141592653589793},"translation":{"x":3.774212863999999,"y":3.0}},"time":1.725808323451598,"velocity":1.0,"position":1.225787136000001,"holonomicRotation":144.71999999999997,"angularVelocity":0.0,"angularAcceleration":0.0,"curveRadius":0.0},{"acceleration":0.0,"curvature":0,"pose":{"rotation":{"radians":3.141592653589793},"translation":{"x":3.7630734079999995,"y":3.0}},"time":1.7369477794515975,"velocity":1.0,"position":1.2369265920000005,"holonomicRotation":144.35999999999996,"angularVelocity":0.0,"angularAcceleration":0.0,"curveRadius":0.0},{"acceleration":0.0,"curvature":0,"pose":{"rotation":{"radians":3.141592653589793},"translation":{"x":3.7519999999999993,"y":3.0}},"time":1.7480211874515976,"velocity":1.0,"position":1.2480000000000007,"holonomicRotation":143.99999999999997,"angularVelocity":0.0,"angularAcceleration":0.0,"curveRadius":0.0},{"acceleration":0.0,"curvature":0,"pose":{"rotation":{"radians":3.141592653589793},"translation":{"x":3.7409937919999994,"y":3.0}},"time":1.7590273954515976,"velocity":1.0,"position":1.2590062080000006,"holonomicRotation":143.64,"angularVelocity":0.0,"angularAcceleration":0.0,"curveRadius":0.0},{"acceleration":0.0,"curvature":0,"pose":{"rotation":{"radians":3.141592653589793},"translation":{"x":3.7300559359999994,"y":3.0}},"time":1.7699652514515976,"velocity":1.0,"position":1.2699440640000006,"holonomicRotation":143.27999999999997,"angularVelocity":0.0,"angularAcceleration":0.0,"curveRadius":0.0},{"acceleration":0.0,"curvature":0,"pose":{"rotation":{"radians":3.141592653589793},"translation":{"x":3.7191875839999993,"y":3.0}},"time":1.7808336034515977,"velocity":1.0,"position":1.2808124160000007,"holonomicRotation":142.91999999999996,"angularVelocity":0.0,"angularAcceleration":0.0,"curveRadius":0.0},{"acceleration":0.0,"curvature":0,"pose":{"rotation":{"radians":3.141592653589793},"translation":{"x":3.7083898879999992,"y":3.0}},"time":1.7916312994515977,"velocity":1.0,"position":1.2916101120000008,"holonomicRotation":142.55999999999997,"angularVelocity":0.0,"angularAcceleration":0.0,"curveRadius":0.0},{"acceleration":0.0,"curvature":0,"pose":{"rotation":{"radians":3.141592653589793},"translation":{"x":3.6976639999999996,"y":3.0}},"time":1.8023571874515973,"velocity":1.0,"position":1.3023360000000004,"holonomicRotation":142.2,"angularVelocity":0.0,"angularAcceleration":0.0,"curveRadius":0.0},{"acceleration":0.0,"curvature":0,"pose":{"rotation":{"radians":3.141592653589793},"translation":{"x":3.687011071999999,"y":3.0}},"time":1.813010115451598,"velocity":1.0,"position":1.312988928000001,"holonomicRotation":141.83999999999997,"angularVelocity":0.0,"angularAcceleration":0.0,"curveRadius":0.0},{"acceleration":0.0,"curvature":0,"pose":{"rotation":{"radians":3.141592653589793},"translation":{"x":3.6764322559999996,"y":3.0}},"time":1.8235889314515974,"velocity":1.0,"position":1.3235677440000004,"holonomicRotation":141.47999999999996,"angularVelocity":0.0,"angularAcceleration":0.0,"curveRadius":0.0},{"acceleration":0.0,"curvature":0,"pose":{"rotation":{"radians":3.141592653589793},"translation":{"x":3.6659287039999993,"y":3.0}},"time":1.8340924834515977,"velocity":1.0,"position":1.3340712960000007,"holonomicRotation":141.11999999999998,"angularVelocity":0.0,"angularAcceleration":0.0,"curveRadius":0.0},{"acceleration":0.0,"curvature":0,"pose":{"rotation":{"radians":3.141592653589793},"translation":{"x":3.6555015679999996,"y":3.0}},"time":1.8445196194515974,"velocity":1.0,"position":1.3444984320000004,"holonomicRotation":140.75999999999996,"angularVelocity":0.0,"angularAcceleration":0.0,"curveRadius":0.0},{"acceleration":0.0,"curvature":0,"pose":{"rotation":{"radians":3.141592653589793},"translation":{"x":3.645151999999999,"y":3.0}},"time":1.854869187451598,"velocity":1.0,"position":1.354848000000001,"holonomicRotation":140.39999999999998,"angularVelocity":0.0,"angularAcceleration":0.0,"curveRadius":0.0},{"acceleration":0.0,"curvature":0,"pose":{"rotation":{"radians":3.141592653589793},"translation":{"x":3.6348811519999997,"y":3.0}},"time":1.8651400354515972,"velocity":1.0,"position":1.3651188480000003,"holonomicRotation":140.03999999999996,"angularVelocity":0.0,"angularAcceleration":0.0,"curveRadius":0.0},{"acceleration":0.0,"curvature":0,"pose":{"rotation":{"radians":3.141592653589793},"translation":{"x":3.624690175999999,"y":3.0}},"time":1.8753310114515978,"velocity":1.0,"position":1.3753098240000008,"holonomicRotation":139.67999999999998,"angularVelocity":0.0,"angularAcceleration":0.0,"curveRadius":0.0},{"acceleration":0.0,"curvature":0,"pose":{"rotation":{"radians":3.141592653589793},"translation":{"x":3.6145802239999996,"y":3.0}},"time":1.8854409634515974,"velocity":1.0,"position":1.3854197760000004,"holonomicRotation":139.31999999999996,"angularVelocity":0.0,"angularAcceleration":0.0,"curveRadius":0.0},{"acceleration":0.0,"curvature":0,"pose":{"rotation":{"radians":3.141592653589793},"translation":{"x":3.604552447999999,"y":3.0}},"time":1.895468739451598,"velocity":1.0,"position":1.3954475520000011,"holonomicRotation":138.95999999999998,"angularVelocity":0.0,"angularAcceleration":0.0,"curveRadius":0.0},{"acceleration":0.0,"curvature":0,"pose":{"rotation":{"radians":3.141592653589793},"translation":{"x":3.594607999999999,"y":3.0}},"time":1.9054131874515978,"velocity":1.0,"position":1.4053920000000009,"holonomicRotation":138.59999999999997,"angularVelocity":0.0,"angularAcceleration":0.0,"curveRadius":0.0},{"acceleration":0.0,"curvature":0,"pose":{"rotation":{"radians":3.141592653589793},"translation":{"x":3.584748031999999,"y":3.0}},"time":1.915273155451598,"velocity":1.0,"position":1.415251968000001,"holonomicRotation":138.23999999999995,"angularVelocity":0.0,"angularAcceleration":0.0,"curveRadius":0.0},{"acceleration":0.0,"curvature":0,"pose":{"rotation":{"radians":3.141592653589793},"translation":{"x":3.5749736959999994,"y":3.0}},"time":1.9250474914515976,"velocity":1.0,"position":1.4250263040000006,"holonomicRotation":137.87999999999997,"angularVelocity":0.0,"angularAcceleration":0.0,"curveRadius":0.0},{"acceleration":0.0,"curvature":0,"pose":{"rotation":{"radians":3.141592653589793},"translation":{"x":3.565286143999999,"y":3.0}},"time":1.934735043451598,"velocity":1.0,"position":1.434713856000001,"holonomicRotation":137.51999999999998,"angularVelocity":0.0,"angularAcceleration":0.0,"curveRadius":0.0},{"acceleration":0.0,"curvature":0,"pose":{"rotation":{"radians":3.141592653589793},"translation":{"x":3.555686527999999,"y":3.0}},"time":1.944334659451598,"velocity":1.0,"position":1.444313472000001,"holonomicRotation":137.15999999999997,"angularVelocity":0.0,"angularAcceleration":0.0,"curveRadius":0.0},{"acceleration":0.0,"curvature":0,"pose":{"rotation":{"radians":3.141592653589793},"translation":{"x":3.546175999999999,"y":3.0}},"time":1.9538451874515979,"velocity":1.0,"position":1.453824000000001,"holonomicRotation":136.79999999999995,"angularVelocity":0.0,"angularAcceleration":0.0,"curveRadius":0.0},{"acceleration":0.0,"curvature":0,"pose":{"rotation":{"radians":3.141592653589793},"translation":{"x":3.5367557119999993,"y":3.0}},"time":1.9632654754515977,"velocity":1.0,"position":1.4632442880000007,"holonomicRotation":136.43999999999997,"angularVelocity":0.0,"angularAcceleration":0.0,"curveRadius":0.0},{"acceleration":0.0,"curvature":0,"pose":{"rotation":{"radians":3.141592653589793},"translation":{"x":3.5274268159999993,"y":3.0}},"time":1.9725943714515977,"velocity":1.0,"position":1.4725731840000007,"holonomicRotation":136.07999999999996,"angularVelocity":0.0,"angularAcceleration":0.0,"curveRadius":0.0},{"acceleration":0.0,"curvature":0,"pose":{"rotation":{"radians":3.141592653589793},"translation":{"x":3.5181904639999995,"y":3.0}},"time":1.9818307234515975,"velocity":1.0,"position":1.4818095360000005,"holonomicRotation":135.71999999999997,"angularVelocity":0.0,"angularAcceleration":0.0,"curveRadius":0.0},{"acceleration":0.0,"curvature":0,"pose":{"rotation":{"radians":3.141592653589793},"translation":{"x":3.509047807999999,"y":3.0}},"time":1.9909733794515978,"velocity":1.0,"position":1.4909521920000008,"holonomicRotation":135.35999999999996,"angularVelocity":0.0,"angularAcceleration":0.0,"curveRadius":0.0},{"acceleration":2.7240798154292127e-12,"curvature":0,"pose":{"rotation":{"radians":3.141592653589793},"translation":{"x":3.499999999999999,"y":3.0}},"time":2.0000211874515976,"velocity":1.0000000000000246,"position":1.5000000000000009,"holonomicRotation":134.99999999999997,"angularVelocity":0.0,"angularAcceleration":0.0,"curveRadius":0.0},{"acceleration":-2.753293094163616e-12,"curvature":0,"pose":{"rotation":{"radians":3.141592653589793},"translation":{"x":3.491048191999999,"y":3.0}},"time":2.0089729954515976,"velocity":1.0,"position":1.5089518080000008,"holonomicRotation":134.64,"angularVelocity":0.0,"angularAcceleration":0.0,"curveRadius":0.0},{"acceleration":0.0,"curvature":0,"pose":{"rotation":{"radians":3.141592653589793},"translation":{"x":3.4821935359999996,"y":3.0}},"time":2.017827651451597,"velocity":1.0,"position":1.5178064640000004,"holonomicRotation":134.27999999999997,"angularVelocity":0.0,"angularAcceleration":0.0,"curveRadius":0.0},{"acceleration":0.0,"curvature":0,"pose":{"rotation":{"radians":3.141592653589793},"translation":{"x":3.4734371839999993,"y":3.0}},"time":2.0265840034515974,"velocity":1.0,"position":1.5265628160000007,"holonomicRotation":133.91999999999996,"angularVelocity":0.0,"angularAcceleration":0.0,"curveRadius":0.0},{"acceleration":0.0,"curvature":0,"pose":{"rotation":{"radians":3.141592653589793},"translation":{"x":3.464780287999999,"y":3.0}},"time":2.0352408994515976,"velocity":1.0,"position":1.5352197120000008,"holonomicRotation":133.55999999999997,"angularVelocity":0.0,"angularAcceleration":0.0,"curveRadius":0.0},{"acceleration":0.0,"curvature":0,"pose":{"rotation":{"radians":3.141592653589793},"translation":{"x":3.4562239999999993,"y":3.0}},"time":2.0437971874515974,"velocity":1.0,"position":1.5437760000000007,"holonomicRotation":133.19999999999996,"angularVelocity":0.0,"angularAcceleration":0.0,"curveRadius":0.0},{"acceleration":0.0,"curvature":0,"pose":{"rotation":{"radians":3.141592653589793},"translation":{"x":3.4477694719999996,"y":3.0}},"time":2.052251715451597,"velocity":1.0,"position":1.5522305280000004,"holonomicRotation":132.83999999999997,"angularVelocity":0.0,"angularAcceleration":0.0,"curveRadius":0.0},{"acceleration":0.0,"curvature":0,"pose":{"rotation":{"radians":3.141592653589793},"translation":{"x":3.439417855999999,"y":3.0}},"time":2.0606033314515977,"velocity":1.0,"position":1.560582144000001,"holonomicRotation":132.47999999999996,"angularVelocity":0.0,"angularAcceleration":0.0,"curveRadius":0.0},{"acceleration":0.0,"curvature":0,"pose":{"rotation":{"radians":3.141592653589793},"translation":{"x":3.4311703039999992,"y":3.0}},"time":2.0688508834515975,"velocity":1.0,"position":1.5688296960000008,"holonomicRotation":132.11999999999998,"angularVelocity":0.0,"angularAcceleration":0.0,"curveRadius":0.0},{"acceleration":0.0,"curvature":0,"pose":{"rotation":{"radians":3.141592653589793},"translation":{"x":3.4230279679999995,"y":3.0}},"time":2.076993219451597,"velocity":1.0,"position":1.5769720320000005,"holonomicRotation":131.75999999999996,"angularVelocity":0.0,"angularAcceleration":0.0,"curveRadius":0.0},{"acceleration":0.0,"curvature":0,"pose":{"rotation":{"radians":3.141592653589793},"translation":{"x":3.4149919999999994,"y":3.0}},"time":2.0850291874515974,"velocity":1.0,"position":1.5850080000000006,"holonomicRotation":131.39999999999998,"angularVelocity":0.0,"angularAcceleration":0.0,"curveRadius":0.0},{"acceleration":0.0,"curvature":0,"pose":{"rotation":{"radians":3.141592653589793},"translation":{"x":3.4070635519999994,"y":3.0}},"time":2.0929576354515973,"velocity":1.0,"position":1.5929364480000006,"holonomicRotation":131.03999999999996,"angularVelocity":0.0,"angularAcceleration":0.0,"curveRadius":0.0},{"acceleration":0.0,"curvature":0,"pose":{"rotation":{"radians":3.141592653589793},"translation":{"x":3.3992437759999996,"y":3.0}},"time":2.100777411451597,"velocity":1.0,"position":1.6007562240000004,"holonomicRotation":130.67999999999995,"angularVelocity":0.0,"angularAcceleration":0.0,"curveRadius":0.0},{"acceleration":0.0,"curvature":0,"pose":{"rotation":{"radians":3.141592653589793},"translation":{"x":3.3915338239999993,"y":3.0}},"time":2.1084873634515975,"velocity":1.0,"position":1.6084661760000007,"holonomicRotation":130.31999999999996,"angularVelocity":0.0,"angularAcceleration":0.0,"curveRadius":0.0},{"acceleration":0.0,"curvature":0,"pose":{"rotation":{"radians":3.141592653589793},"translation":{"x":3.383934847999999,"y":3.0}},"time":2.1160863394515976,"velocity":1.0,"position":1.616065152000001,"holonomicRotation":129.95999999999998,"angularVelocity":0.0,"angularAcceleration":0.0,"curveRadius":0.0},{"acceleration":0.0,"curvature":0,"pose":{"rotation":{"radians":3.141592653589793},"translation":{"x":3.3764479999999994,"y":3.0}},"time":2.1235731874515973,"velocity":1.0,"position":1.6235520000000006,"holonomicRotation":129.59999999999997,"angularVelocity":0.0,"angularAcceleration":0.0,"curveRadius":0.0},{"acceleration":0.0,"curvature":0,"pose":{"rotation":{"radians":3.141592653589793},"translation":{"x":3.3690744319999992,"y":3.0}},"time":2.1309467554515975,"velocity":1.0,"position":1.6309255680000008,"holonomicRotation":129.23999999999995,"angularVelocity":0.0,"angularAcceleration":0.0,"curveRadius":0.0},{"acceleration":0.0,"curvature":0,"pose":{"rotation":{"radians":3.141592653589793},"translation":{"x":3.3618152959999996,"y":3.0}},"time":2.138205891451597,"velocity":1.0,"position":1.6381847040000004,"holonomicRotation":128.87999999999997,"angularVelocity":0.0,"angularAcceleration":0.0,"curveRadius":0.0},{"acceleration":0.0,"curvature":0,"pose":{"rotation":{"radians":3.141592653589793},"translation":{"x":3.3546717439999996,"y":3.0}},"time":2.145349443451597,"velocity":1.0,"position":1.6453282560000004,"holonomicRotation":128.51999999999998,"angularVelocity":0.0,"angularAcceleration":0.0,"curveRadius":0.0},{"acceleration":-0.33245896861300095,"curvature":0,"pose":{"rotation":{"radians":3.141592653589793},"translation":{"x":3.347644927999999,"y":3.0}},"time":2.1523927521417083,"velocity":0.9976583888572627,"position":1.652355072000001,"holonomicRotation":128.15999999999997,"angularVelocity":0.0,"angularAcceleration":0.0,"curveRadius":0.0},{"acceleration":-0.8361576855475702,"curvature":0,"pose":{"rotation":{"radians":3.141592653589793},"translation":{"x":3.3407359999999997,"y":3.0}},"time":2.159358563852746,"velocity":0.9918338718590013,"position":1.6592640000000003,"holonomicRotation":127.79999999999995,"angularVelocity":0.0,"angularAcceleration":0.0,"curveRadius":0.0},{"acceleration":-1.0052112584433601,"curvature":0,"pose":{"rotation":{"radians":3.141592653589793},"translation":{"x":3.3339461119999996,"y":3.0}},"time":2.1662525231564866,"velocity":0.9849039863516308,"position":1.6660538880000004,"holonomicRotation":127.43999999999997,"angularVelocity":0.0,"angularAcceleration":0.0,"curveRadius":0.0},{"acceleration":-1.0054666906001466,"curvature":0,"pose":{"rotation":{"radians":3.141592653589793},"translation":{"x":3.3272764159999997,"y":3.0}},"time":2.1730719233582967,"velocity":0.9780473065988389,"position":1.6727235840000003,"holonomicRotation":127.07999999999996,"angularVelocity":0.0,"angularAcceleration":0.0,"curveRadius":0.0},{"acceleration":-1.0057345296111126,"curvature":0,"pose":{"rotation":{"radians":3.141592653589793},"translation":{"x":3.320728063999999,"y":3.0}},"time":2.179813998303357,"velocity":0.9712665690253657,"position":1.679271936000001,"holonomicRotation":126.71999999999997,"angularVelocity":0.0,"angularAcceleration":0.0,"curveRadius":0.0},{"acceleration":-1.0060155889532554,"curvature":0,"pose":{"rotation":{"radians":3.141592653589793},"translation":{"x":3.3143022079999995,"y":3.0}},"time":2.1864759224537322,"velocity":0.9645645694776641,"position":1.6856977920000005,"holonomicRotation":126.35999999999996,"angularVelocity":0.0,"angularAcceleration":0.0,"curveRadius":0.0},{"acceleration":-1.0063107528871686,"curvature":0,"pose":{"rotation":{"radians":3.141592653589793},"translation":{"x":3.3079999999999994,"y":3.0}},"time":2.1930548111227925,"velocity":0.9579441630679412,"position":1.6920000000000006,"holonomicRotation":125.99999999999997,"angularVelocity":0.0,"angularAcceleration":0.0,"curveRadius":0.0},{"acceleration":-1.0066209846182337,"curvature":0,"pose":{"rotation":{"radians":3.141592653589793},"translation":{"x":3.3018225919999993,"y":3.0}},"time":2.1995477208805583,"velocity":0.9514082638545417,"position":1.6981774080000007,"holonomicRotation":125.63999999999996,"angularVelocity":0.0,"angularAcceleration":0.0,"curveRadius":0.0},{"acceleration":-1.0069473358144594,"curvature":0,"pose":{"rotation":{"radians":3.141592653589793},"translation":{"x":3.295771135999999,"y":3.0}},"time":2.2059516501440304,"velocity":0.9449598443439442,"position":1.704228864000001,"holonomicRotation":125.27999999999996,"angularVelocity":0.0,"angularAcceleration":0.0,"curveRadius":0.0},{"acceleration":-1.0072909574832027,"curvature":0,"pose":{"rotation":{"radians":3.141592653589793},"translation":{"x":3.2898467839999994,"y":3.0}},"time":2.2122635399669055,"velocity":0.9386019348007318,"position":1.7101532160000006,"holonomicRotation":124.91999999999996,"angularVelocity":0.0,"angularAcceleration":0.0,"curveRadius":0.0},{"acceleration":-1.0076531125403045,"curvature":0,"pose":{"rotation":{"radians":3.141592653589793},"translation":{"x":3.2840506879999998,"y":3.0}},"time":2.218480275043394,"velocity":0.9323376223510699,"position":1.7159493120000002,"holonomicRotation":124.55999999999996,"angularVelocity":0.0,"angularAcceleration":0.0,"curveRadius":0.0},{"acceleration":-1.008035190550748,"curvature":0,"pose":{"rotation":{"radians":3.141592653589793},"translation":{"x":3.2783839999999995,"y":3.0}},"time":2.2245986849410495,"velocity":0.926170049864019,"position":1.7216160000000005,"holonomicRotation":124.19999999999996,"angularVelocity":0.0,"angularAcceleration":0.0,"curveRadius":0.0},{"acceleration":-1.0084387247122966,"curvature":0,"pose":{"rotation":{"radians":3.141592653589793},"translation":{"x":3.2728478719999994,"y":3.0}},"time":2.2306155455776184,"velocity":0.9201024145969058,"position":1.7271521280000006,"holonomicRotation":123.83999999999996,"angularVelocity":0.0,"angularAcceleration":0.0,"curveRadius":0.0},{"acceleration":-1.008865411882383,"curvature":0,"pose":{"rotation":{"radians":3.141592653589793},"translation":{"x":3.2674434559999996,"y":3.0}},"time":2.2365275809568796,"velocity":0.9141379665889442,"position":1.7325565440000004,"holonomicRotation":123.47999999999996,"angularVelocity":0.0,"angularAcceleration":0.0,"curveRadius":0.0},{"acceleration":-1.0093171360485722,"curvature":0,"pose":{"rotation":{"radians":3.141592653589793},"translation":{"x":3.2621719039999997,"y":3.0}},"time":2.2423314651782644,"velocity":0.9082800067886586,"position":1.7378280960000003,"holonomicRotation":123.11999999999996,"angularVelocity":0.0,"angularAcceleration":0.0,"curveRadius":0.0},{"acceleration":-1.009795996184544,"curvature":0,"pose":{"rotation":{"radians":3.141592653589793},"translation":{"x":3.2570343679999993,"y":3.0}},"time":2.248023824734704,"velocity":0.9025318848997231,"position":1.7429656320000007,"holonomicRotation":122.75999999999996,"angularVelocity":0.0,"angularAcceleration":0.0,"curveRadius":0.0},{"acceleration":-1.010304339025607,"curvature":0,"pose":{"rotation":{"radians":3.141592653589793},"translation":{"x":3.2520319999999994,"y":3.0}},"time":2.253601241112625,"velocity":0.8968969969325569,"position":1.7479680000000006,"holonomicRotation":122.39999999999995,"angularVelocity":0.0,"angularAcceleration":0.0,"curveRadius":0.0},{"acceleration":-1.0108447985103588,"curvature":0,"pose":{"rotation":{"radians":3.141592653589793},"translation":{"x":3.2471659519999996,"y":3.0}},"time":2.2590602537073,"velocity":0.8913787824462274,"position":1.7528340480000004,"holonomicRotation":122.03999999999996,"angularVelocity":0.0,"angularAcceleration":0.0,"curveRadius":0.0},{"acceleration":-1.0114203427242252,"curvature":0,"pose":{"rotation":{"radians":3.141592653589793},"translation":{"x":3.2424373759999994,"y":3.0}},"time":2.2643973630657928,"velocity":0.8859807214697039,"position":1.7575626240000006,"holonomicRotation":121.67999999999995,"angularVelocity":0.0,"angularAcceleration":0.0,"curveRadius":0.0},{"acceleration":-1.0120343308313584,"curvature":0,"pose":{"rotation":{"radians":3.141592653589793},"translation":{"x":3.2378474239999995,"y":3.0}},"time":2.2696090344685906,"velocity":0.8807063310890604,"position":1.7621525760000005,"holonomicRotation":121.31999999999996,"angularVelocity":0.0,"angularAcceleration":0.0,"curveRadius":0.0},{"acceleration":-1.012690581735746,"curvature":0,"pose":{"rotation":{"radians":3.141592653589793},"translation":{"x":3.2333972479999993,"y":3.0}},"time":2.2746917018595636,"velocity":0.8755591616921267,"position":1.7666027520000007,"holonomicRotation":120.95999999999995,"angularVelocity":0.0,"angularAcceleration":0.0,"curveRadius":0.0},{"acceleration":-1.0133934581769353,"curvature":0,"pose":{"rotation":{"radians":3.141592653589793},"translation":{"x":3.2290879999999995,"y":3.0}},"time":2.2796417721322046,"velocity":0.8705427928603161,"position":1.7709120000000005,"holonomicRotation":120.59999999999997,"angularVelocity":0.0,"angularAcceleration":0.0,"curveRadius":0.0},{"acceleration":-1.0141479699497775,"curvature":0,"pose":{"rotation":{"radians":3.141592653589793},"translation":{"x":3.2249208319999996,"y":3.0}},"time":2.284455629778149,"velocity":0.8656608289010543,"position":1.7750791680000004,"holonomicRotation":120.23999999999995,"angularVelocity":0.0,"angularAcceleration":0.0,"curveRadius":0.0},{"acceleration":-1.0149599015499695,"curvature":0,"pose":{"rotation":{"radians":3.141592653589793},"translation":{"x":3.2208968959999997,"y":3.0}},"time":2.2891296419016975,"velocity":0.8609168940162942,"position":1.7791031040000003,"holonomicRotation":119.87999999999997,"angularVelocity":0.0,"angularAcceleration":0.0,"curveRadius":0.0},{"acceleration":-1.0158359713556468,"curvature":0,"pose":{"rotation":{"radians":3.141592653589793},"translation":{"x":3.2170173439999994,"y":3.0}},"time":2.2936601636015523,"velocity":0.8563146271045744,"position":1.7829826560000006,"holonomicRotation":119.51999999999995,"angularVelocity":0.0,"angularAcceleration":0.0,"curveRadius":0.0},{"acceleration":-1.0167840318749934,"curvature":0,"pose":{"rotation":{"radians":3.141592653589793},"translation":{"x":3.2132833279999997,"y":3.0}},"time":2.2980435437181375,"velocity":0.8518576761963923,"position":1.7867166720000003,"holonomicRotation":119.15999999999995,"angularVelocity":0.0,"angularAcceleration":0.0,"curveRadius":0.0},{"acceleration":-1.0178133237508438,"curvature":0,"pose":{"rotation":{"radians":3.141592653589793},"translation":{"x":3.209696,"y":3.0}},"time":2.302276130941793,"velocity":0.8475496925262181,"position":1.790304,"holonomicRotation":118.79999999999995,"angularVelocity":0.0,"angularAcceleration":0.0,"curveRadius":0.0},{"acceleration":-1.0189348009463555,"curvature":0,"pose":{"rotation":{"radians":3.141592653589793},"translation":{"x":3.2062565119999995,"y":3.0}},"time":2.3063542802737387,"velocity":0.8433943242484425,"position":1.7937434880000005,"holonomicRotation":118.43999999999996,"angularVelocity":0.0,"angularAcceleration":0.0,"curveRadius":0.0},{"acceleration":-1.0201615522492862,"curvature":0,"pose":{"rotation":{"radians":3.141592653589793},"translation":{"x":3.2029660159999995,"y":3.0}},"time":2.310274359828116,"velocity":0.8393952098053084,"position":1.7970339840000005,"holonomicRotation":118.07999999999996,"angularVelocity":0.0,"angularAcceleration":0.0,"curveRadius":0.0},{"acceleration":-1.021509352816525,"curvature":0,"pose":{"rotation":{"radians":3.141592653589793},"translation":{"x":3.1998256639999996,"y":3.0}},"time":2.3140327579595814,"velocity":0.8355559709624082,"position":1.8001743360000004,"holonomicRotation":117.71999999999996,"angularVelocity":0.0,"angularAcceleration":0.0,"curveRadius":0.0},{"acceleration":-1.022997396200092,"curvature":0,"pose":{"rotation":{"radians":3.141592653589793},"translation":{"x":3.196836608,"y":3.0}},"time":2.317625890696888,"velocity":0.8318802055279424,"position":1.803163392,"holonomicRotation":117.35999999999996,"angularVelocity":0.0,"angularAcceleration":0.0,"curveRadius":0.0},{"acceleration":-1.0246492787462347,"curvature":0,"pose":{"rotation":{"radians":3.141592653589793},"translation":{"x":3.194,"y":3.0}},"time":2.321050209458754,"velocity":0.8283714797783991,"position":1.806,"holonomicRotation":116.99999999999996,"angularVelocity":0.0,"angularAcceleration":0.0,"curveRadius":0.0},{"acceleration":-1.026494344952022,"curvature":0,"pose":{"rotation":{"radians":3.141592653589793},"translation":{"x":3.191316992,"y":3.0}},"time":2.324302209024057,"velocity":0.825033320614829,"position":1.808683008,"holonomicRotation":116.63999999999996,"angularVelocity":0.0,"angularAcceleration":0.0,"curveRadius":0.0},{"acceleration":-1.0285695565581667,"curvature":0,"pose":{"rotation":{"radians":3.141592653589793},"translation":{"x":3.188788736,"y":3.0}},"time":2.3273784357241007,"velocity":0.8218692074820927,"position":1.8112112640000002,"holonomicRotation":116.27999999999994,"angularVelocity":0.0,"angularAcceleration":0.0,"curveRadius":0.0},{"acceleration":-1.0309221413473277,"curvature":0,"pose":{"rotation":{"radians":3.141592653589793},"translation":{"x":3.1864163839999997,"y":3.0}},"time":2.3302754958204455,"velocity":0.8188825640839571,"position":1.8135836160000003,"holonomicRotation":115.91999999999996,"angularVelocity":0.0,"angularAcceleration":0.0,"curveRadius":0.0},{"acceleration":-1.033613428612105,"curvature":0,"pose":{"rotation":{"radians":3.141592653589793},"translation":{"x":3.1842010879999996,"y":3.0}},"time":2.3329900640276446,"velocity":0.8160767499321125,"position":1.8157989120000004,"holonomicRotation":115.55999999999996,"angularVelocity":0.0,"angularAcceleration":0.0,"curveRadius":0.0},{"acceleration":-1.0367245400806269,"curvature":0,"pose":{"rotation":{"radians":3.141592653589793},"translation":{"x":3.1821439999999996,"y":3.0}},"time":2.335518892136233,"velocity":0.8134550517742934,"position":1.8178560000000004,"holonomicRotation":115.19999999999995,"angularVelocity":0.0,"angularAcceleration":0.0,"curveRadius":0.0},{"acceleration":-1.0403650785001255,"curvature":0,"pose":{"rotation":{"radians":3.141592653589793},"translation":{"x":3.180246272,"y":3.0}},"time":2.3378588176876125,"velocity":0.8110206749443479,"position":1.8197537279999998,"holonomicRotation":114.83999999999995,"angularVelocity":0.0,"angularAcceleration":0.0,"curveRadius":0.0},{"acceleration":-1.044686828487171,"curvature":0,"pose":{"rotation":{"radians":3.141592653589793},"translation":{"x":3.178509056,"y":3.0}},"time":2.3400067726490894,"velocity":0.8087767346879093,"position":1.8214909439999998,"holonomicRotation":114.47999999999995,"angularVelocity":0.0,"angularAcceleration":0.0,"curveRadius":0.0},{"acceleration":-1.049906206197387,"curvature":0,"pose":{"rotation":{"radians":3.141592653589793},"translation":{"x":3.176933504,"y":3.0}},"time":2.3419597920343573,"velocity":0.8067262475144927,"position":1.823066496,"holonomicRotation":114.11999999999995,"angularVelocity":0.0,"angularAcceleration":0.0,"curveRadius":0.0},{"acceleration":-1.0563427484270644,"curvature":0,"pose":{"rotation":{"radians":3.141592653589793},"translation":{"x":3.1755207679999997,"y":3.0}},"time":2.3437150224122947,"velocity":0.8048721226329397,"position":1.8244792320000003,"holonomicRotation":113.75999999999995,"angularVelocity":0.0,"angularAcceleration":0.0,"curveRadius":0.0},{"acceleration":-1.064488819426518,"curvature":0,"pose":{"rotation":{"radians":3.141592653589793},"translation":{"x":3.1742719999999998,"y":3.0}},"time":2.345269730245059,"velocity":0.8032171535274871,"position":1.8257280000000002,"holonomicRotation":113.39999999999995,"angularVelocity":0.0,"angularAcceleration":0.0,"curveRadius":0.0},{"acceleration":-1.0751446899003774,"curvature":0,"pose":{"rotation":{"radians":3.141592653589793},"translation":{"x":3.173188352,"y":3.0}},"time":2.346621309995261,"velocity":0.8017640097360809,"position":1.826811648,"holonomicRotation":113.03999999999995,"angularVelocity":0.0,"angularAcceleration":0.0,"curveRadius":0.0},{"acceleration":-1.0897037709999702,"curvature":0,"pose":{"rotation":{"radians":3.141592653589793},"translation":{"x":3.172270976,"y":3.0}},"time":2.3477672919415062,"velocity":0.8005152288877594,"position":1.827729024,"holonomicRotation":112.67999999999995,"angularVelocity":0.0,"angularAcceleration":0.0,"curveRadius":0.0},{"acceleration":-1.1108270021236468,"curvature":0,"pose":{"rotation":{"radians":3.141592653589793},"translation":{"x":3.171521024,"y":3.0}},"time":2.348705349641873,"velocity":0.7994732090646419,"position":1.828478976,"holonomicRotation":112.31999999999995,"angularVelocity":0.0,"angularAcceleration":0.0,"curveRadius":0.0},{"acceleration":-1.1443081511848496,"curvature":0,"pose":{"rotation":{"radians":3.141592653589793},"translation":{"x":3.170939648,"y":3.0}},"time":2.3494333069859654,"velocity":0.7986402015420822,"position":1.829060352,"holonomicRotation":111.95999999999995,"angularVelocity":0.0,"angularAcceleration":0.0,"curveRadius":0.0},{"acceleration":-1.2056068343892758,"curvature":0,"pose":{"rotation":{"radians":3.141592653589793},"translation":{"x":3.170528,"y":3.0}},"time":2.3499491447780936,"velocity":0.7980183039744562,"position":1.829472,"holonomicRotation":111.59999999999995,"angularVelocity":0.0,"angularAcceleration":0.0,"curveRadius":0.0},{"acceleration":-1.3544264609175796,"curvature":0,"pose":{"rotation":{"radians":3.141592653589793},"translation":{"x":3.170287232,"y":3.0}},"time":2.3502510067968694,"velocity":0.7976094540686802,"position":1.8297127679999998,"holonomicRotation":111.23999999999995,"angularVelocity":0.0,"angularAcceleration":0.0,"curveRadius":0.0},{"acceleration":-2.2509706131641853,"curvature":0,"pose":{"rotation":{"radians":3.141592653589793},"translation":{"x":3.170218496,"y":3.0}},"time":2.350337205280053,"velocity":0.7974154238161344,"position":1.829781504,"holonomicRotation":110.87999999999995,"angularVelocity":0.0,"angularAcceleration":0.0,"curveRadius":0.0},{"acceleration":-0.8289993008841153,"curvature":0,"pose":{"rotation":{"radians":0.0},"translation":{"x":3.170322944,"y":3.0}},"time":2.350468206291015,"velocity":0.7973068240696317,"position":1.8298859520000001,"holonomicRotation":110.51999999999995,"angularVelocity":-23981.43823866422,"angularAcceleration":-183063001.28939638,"curveRadius":0.0},{"acceleration":-0.6872713424131556,"curvature":0,"pose":{"rotation":{"radians":0.0},"translation":{"x":3.1706017280000003,"y":3.0}},"time":2.350817968851839,"velocity":0.7970664422849285,"position":1.8301647360000004,"holonomicRotation":110.15999999999995,"angularVelocity":0.0,"angularAcceleration":68564909.24066812,"curveRadius":0.0},{"acceleration":-0.8066699090394802,"curvature":0,"pose":{"rotation":{"radians":0.0},"translation":{"x":3.171056,"y":3.0}},"time":2.3513882278681346,"velocity":0.7966064314961243,"position":1.8306190080000002,"holonomicRotation":109.79999999999995,"angularVelocity":0.0,"angularAcceleration":0.0,"curveRadius":0.0},{"acceleration":-0.8597041953411967,"curvature":0,"pose":{"rotation":{"radians":0.0},"translation":{"x":3.171686912,"y":3.0}},"time":2.3521809056069105,"velocity":0.7959249631185451,"position":1.8312499200000003,"holonomicRotation":109.43999999999994,"angularVelocity":0.0,"angularAcceleration":0.0,"curveRadius":0.0},{"acceleration":-0.8896324675304699,"curvature":0,"pose":{"rotation":{"radians":0.0},"translation":{"x":3.1724956160000004,"y":3.0}},"time":2.353198117729246,"velocity":0.79502001818815,"position":1.8320586240000005,"holonomicRotation":109.07999999999994,"angularVelocity":0.0,"angularAcceleration":0.0,"curveRadius":0.0},{"acceleration":-0.9088267794982242,"curvature":0,"pose":{"rotation":{"radians":0.0},"translation":{"x":3.173483264,"y":3.0}},"time":2.3544421802192903,"velocity":0.7938893808818284,"position":1.8330462720000003,"holonomicRotation":108.71999999999994,"angularVelocity":0.0,"angularAcceleration":0.0,"curveRadius":0.0},{"acceleration":-0.9221634322991134,"curvature":0,"pose":{"rotation":{"radians":0.0},"translation":{"x":3.1746510080000006,"y":3.0}},"time":2.3559156172754285,"velocity":0.7925306311088632,"position":1.8342140160000007,"holonomicRotation":108.35999999999994,"angularVelocity":0.0,"angularAcceleration":0.0,"curveRadius":0.0},{"acceleration":-0.9319528874228848,"curvature":0,"pose":{"rotation":{"radians":0.0},"translation":{"x":3.176,"y":3.0}},"time":2.3576211702406646,"velocity":0.7909411360982588,"position":1.8355630080000003,"holonomicRotation":107.99999999999994,"angularVelocity":0.0,"angularAcceleration":0.0,"curveRadius":0.0},{"acceleration":-0.9394311237259001,"curvature":0,"pose":{"rotation":{"radians":0.0},"translation":{"x":3.1775313920000006,"y":3.0}},"time":2.3595618076619616,"velocity":0.7891180409048253,"position":1.8370944000000007,"holonomicRotation":107.63999999999994,"angularVelocity":0.0,"angularAcceleration":0.0,"curveRadius":0.0},{"acceleration":-0.9453191204704766,"curvature":0,"pose":{"rotation":{"radians":0.0},"translation":{"x":3.1792463360000003,"y":3.0}},"time":2.3617407365825946,"velocity":0.7870582577340047,"position":1.8388093440000004,"holonomicRotation":107.27999999999994,"angularVelocity":0.0,"angularAcceleration":0.0,"curveRadius":0.0},{"acceleration":-0.9500657203622258,"curvature":0,"pose":{"rotation":{"radians":0.0},"translation":{"x":3.1811459840000005,"y":3.0}},"time":2.3641614151880788,"velocity":0.78475845397092,"position":1.8407089920000006,"holonomicRotation":106.91999999999994,"angularVelocity":0.0,"angularAcceleration":0.0,"curveRadius":0.0},{"acceleration":-0.9539648951218433,"curvature":0,"pose":{"rotation":{"radians":0.0},"translation":{"x":3.1832314880000006,"y":3.0}},"time":2.366827566945052,"velocity":0.7822150387897001,"position":1.8427944960000007,"holonomicRotation":106.55999999999995,"angularVelocity":0.0,"angularAcceleration":0.0,"curveRadius":0.0},{"acceleration":-0.9572171813079678,"curvature":0,"pose":{"rotation":{"radians":0.0},"translation":{"x":3.185504000000001,"y":3.0}},"time":2.369743196394419,"velocity":0.7794241481864385,"position":1.845067008000001,"holonomicRotation":106.19999999999995,"angularVelocity":0.0,"angularAcceleration":0.0,"curveRadius":0.0},{"acceleration":-0.9599640137459277,"curvature":0,"pose":{"rotation":{"radians":0.0},"translation":{"x":3.1879646720000006,"y":3.0}},"time":2.3729126067854076,"velocity":0.7763816282662971,"position":1.8475276800000007,"holonomicRotation":105.83999999999995,"angularVelocity":0.0,"angularAcceleration":0.0,"curveRadius":0.0},{"acceleration":-0.9623079508956411,"curvature":0,"pose":{"rotation":{"radians":0.0},"translation":{"x":3.1906146560000006,"y":3.0}},"time":2.3763404197668945,"velocity":0.773083016580029,"position":1.8501776640000007,"holonomicRotation":105.47999999999995,"angularVelocity":0.0,"angularAcceleration":0.0,"curveRadius":0.0},{"acceleration":-0.9643251197837451,"curvature":0,"pose":{"rotation":{"radians":0.0},"translation":{"x":3.1934551040000008,"y":3.0}},"time":2.380031597387142,"velocity":0.7695235212792405,"position":1.8530181120000009,"holonomicRotation":105.11999999999995,"angularVelocity":0.0,"angularAcceleration":0.0,"curveRadius":0.0},{"acceleration":-0.9660731622830653,"curvature":0,"pose":{"rotation":{"radians":0.0},"translation":{"x":3.196487168000001,"y":3.0}},"time":2.383991466694167,"velocity":0.7656979978155756,"position":1.856050176000001,"holonomicRotation":104.75999999999995,"angularVelocity":0.0,"angularAcceleration":0.0,"curveRadius":0.0},{"acceleration":-0.9675964699289414,"curvature":0,"pose":{"rotation":{"radians":0.0},"translation":{"x":3.1997120000000003,"y":3.0}},"time":2.3882257472775534,"velocity":0.761600922870402,"position":1.8592750080000005,"holonomicRotation":104.39999999999995,"angularVelocity":0.0,"angularAcceleration":0.0,"curveRadius":0.0},{"acceleration":-0.9689297286223055,"curvature":0,"pose":{"rotation":{"radians":0.0},"translation":{"x":3.2031307520000007,"y":3.0}},"time":2.392740582150423,"velocity":0.7572263651422582,"position":1.8626937600000009,"holonomicRotation":104.03999999999995,"angularVelocity":0.0,"angularAcceleration":0.0,"curveRadius":0.0},{"acceleration":-0.9701003751803976,"curvature":0,"pose":{"rotation":{"radians":0.0},"translation":{"x":3.206744576,"y":3.0}},"time":2.397542572439406,"velocity":0.7525679525613028,"position":1.8663075840000003,"holonomicRotation":103.67999999999994,"angularVelocity":0.0,"angularAcceleration":0.0,"curveRadius":0.0},{"acceleration":-0.971130335830097,"curvature":0,"pose":{"rotation":{"radians":0.0},"translation":{"x":3.2105546240000007,"y":3.0}},"time":2.4026388164336625,"velocity":0.7476188354196885,"position":1.8701176320000008,"holonomicRotation":103.31999999999994,"angularVelocity":0.0,"angularAcceleration":0.0,"curveRadius":0.0},{"acceleration":-0.9720372783575211,"curvature":0,"pose":{"rotation":{"radians":0.0},"translation":{"x":3.214562048000001,"y":3.0}},"time":2.4080369536442863,"velocity":0.7423716448172734,"position":1.874125056000001,"holonomicRotation":102.95999999999994,"angularVelocity":0.0,"angularAcceleration":0.0,"curveRadius":0.0},{"acceleration":-0.9728355279945424,"curvature":0,"pose":{"rotation":{"radians":0.0},"translation":{"x":3.2187680000000007,"y":3.0}},"time":2.413745214647368,"velocity":0.7368184457104098,"position":1.8783310080000009,"holonomicRotation":102.59999999999994,"angularVelocity":0.0,"angularAcceleration":0.0,"curveRadius":0.0},{"acceleration":-0.9735367460423321,"curvature":0,"pose":{"rotation":{"radians":0.0},"translation":{"x":3.223173632000001,"y":3.0}},"time":2.41977247763261,"velocity":0.7309506837162159,"position":1.882736640000001,"holonomicRotation":102.23999999999994,"angularVelocity":0.0,"angularAcceleration":0.0,"curveRadius":0.0},{"acceleration":-0.9741504378677507,"curvature":0,"pose":{"rotation":{"radians":0.0},"translation":{"x":3.227780096000001,"y":3.0}},"time":2.4261283327619507,"velocity":0.7247591246589445,"position":1.887343104000001,"holonomicRotation":101.87999999999994,"angularVelocity":0.0,"angularAcceleration":0.0,"curveRadius":0.0},{"acceleration":-0.9746843358313974,"curvature":0,"pose":{"rotation":{"radians":0.0},"translation":{"x":3.232588544000001,"y":3.0}},"time":2.4328231556679865,"velocity":0.7182337856412663,"position":1.892151552000001,"holonomicRotation":101.51999999999994,"angularVelocity":0.0,"angularAcceleration":0.0,"curveRadius":0.0},{"acceleration":-0.975144688670591,"curvature":0,"pose":{"rotation":{"radians":0.0},"translation":{"x":3.2376001280000013,"y":3.0}},"time":2.439868191701971,"velocity":0.7113638561712334,"position":1.8971631360000014,"holonomicRotation":101.15999999999994,"angularVelocity":0.0,"angularAcceleration":0.0,"curveRadius":0.0},{"acceleration":-0.9755364796285574,"curvature":0,"pose":{"rotation":{"radians":0.0},"translation":{"x":3.2428160000000013,"y":3.0}},"time":2.447275652891379,"velocity":0.704137607559533,"position":1.9023790080000014,"holonomicRotation":100.79999999999994,"angularVelocity":0.0,"angularAcceleration":0.0,"curveRadius":0.0},{"acceleration":-0.975863588752814,"curvature":0,"pose":{"rotation":{"radians":0.0},"translation":{"x":3.248237312000001,"y":3.0}},"time":2.4550588300081664,"velocity":0.6965422884064462,"position":1.907800320000001,"holonomicRotation":100.43999999999994,"angularVelocity":0.0,"angularAcceleration":0.0,"curveRadius":0.0},{"acceleration":-0.976128910109833,"curvature":0,"pose":{"rotation":{"radians":0.0},"translation":{"x":3.2538652160000012,"y":3.0}},"time":2.463232222708643,"velocity":0.6885640034978301,"position":1.9134282240000013,"holonomicRotation":100.07999999999994,"angularVelocity":0.0,"angularAcceleration":0.0,"curveRadius":0.0},{"acceleration":-0.9763344312784086,"curvature":0,"pose":{"rotation":{"radians":0.0},"translation":{"x":3.2597008640000014,"y":3.0}},"time":2.4718116914220394,"velocity":0.6801875727908655,"position":1.9192638720000015,"holonomicRotation":99.71999999999994,"angularVelocity":0.0,"angularAcceleration":0.0,"curveRadius":0.0},{"acceleration":-0.976481279595683,"curvature":0,"pose":{"rotation":{"radians":0.0},"translation":{"x":3.2657454080000012,"y":3.0}},"time":2.4808146355887666,"velocity":0.6713963663508112,"position":1.9253084160000014,"holonomicRotation":99.35999999999994,"angularVelocity":0.0,"angularAcceleration":0.0,"curveRadius":0.0},{"acceleration":-0.9765697375161916,"curvature":0,"pose":{"rotation":{"radians":0.0},"translation":{"x":3.272000000000001,"y":3.0}},"time":2.4902602040523236,"velocity":0.6621721100356641,"position":1.9315630080000012,"holonomicRotation":98.99999999999994,"angularVelocity":0.0,"angularAcceleration":0.0,"curveRadius":0.0},{"acceleration":-0.9765992270589414,"curvature":0,"pose":{"rotation":{"radians":0.0},"translation":{"x":3.2784657920000013,"y":3.0}},"time":2.500169544990422,"velocity":0.6524946553348535,"position":1.9380288000000014,"holonomicRotation":98.63999999999994,"angularVelocity":0.0,"angularAcceleration":0.0,"curveRadius":0.0},{"acceleration":-0.9765682615460188,"curvature":0,"pose":{"rotation":{"radians":0.0},"translation":{"x":3.285143936000001,"y":3.0}},"time":2.51056610487249,"velocity":0.6423417049247634,"position":1.9447069440000013,"holonomicRotation":98.27999999999994,"angularVelocity":0.0,"angularAcceleration":0.0,"curveRadius":0.0},{"acceleration":-0.9764743600337492,"curvature":0,"pose":{"rotation":{"radians":0.0},"translation":{"x":3.2920355840000015,"y":3.0}},"time":2.5214759887551406,"velocity":0.6316884830424098,"position":1.9515985920000016,"holonomicRotation":97.91999999999993,"angularVelocity":0.0,"angularAcceleration":0.0,"curveRadius":0.0},{"acceleration":-0.9763139171171111,"curvature":0,"pose":{"rotation":{"radians":0.0},"translation":{"x":3.299141888000001,"y":3.0}},"time":2.5329283980702826,"velocity":0.620507336443515,"position":1.9587048960000013,"holonomicRotation":97.55999999999993,"angularVelocity":0.0,"angularAcceleration":0.0,"curveRadius":0.0},{"acceleration":-0.976082016493985,"curvature":0,"pose":{"rotation":{"radians":0.0},"translation":{"x":3.3064640000000014,"y":3.0}},"time":2.544956167360416,"velocity":0.6087672471408769,"position":1.9660270080000015,"holonomicRotation":97.19999999999993,"angularVelocity":0.0,"angularAcceleration":0.0,"curveRadius":0.0},{"acceleration":-0.9757721712014331,"curvature":0,"pose":{"rotation":{"radians":0.0},"translation":{"x":3.3140030720000015,"y":3.0}},"time":2.5575964288323587,"velocity":0.5964332317598458,"position":1.9735660800000017,"holonomicRotation":96.83999999999993,"angularVelocity":0.0,"angularAcceleration":0.0,"curveRadius":0.0},{"acceleration":-0.9753759650429036,"curvature":0,"pose":{"rotation":{"radians":0.0},"translation":{"x":3.3217602560000015,"y":3.0}},"time":2.570891444148084,"velocity":0.5834655933660099,"position":1.9813232640000016,"holonomicRotation":96.47999999999993,"angularVelocity":0.0,"angularAcceleration":0.0,"curveRadius":0.0},{"acceleration":-0.9748825573226917,"curvature":0,"pose":{"rotation":{"radians":0.0},"translation":{"x":3.329736704000002,"y":3.0}},"time":2.5848896581388137,"velocity":0.5698189787127772,"position":1.989299712000002,"holonomicRotation":96.11999999999993,"angularVelocity":0.0,"angularAcceleration":0.0,"curveRadius":0.0},{"acceleration":-0.9742779937709075,"curvature":0,"pose":{"rotation":{"radians":0.0},"translation":{"x":3.3379335680000013,"y":3.0}},"time":2.5996470516660057,"velocity":0.5554411749538167,"position":1.9974965760000014,"holonomicRotation":95.75999999999993,"angularVelocity":0.0,"angularAcceleration":0.0,"curveRadius":0.0},{"acceleration":-0.973544235935718,"curvature":0,"pose":{"rotation":{"radians":0.0},"translation":{"x":3.3463520000000013,"y":3.0}},"time":2.6152289048565875,"velocity":0.5402715515949292,"position":2.0059150080000014,"holonomicRotation":95.39999999999993,"angularVelocity":0.0,"angularAcceleration":0.0,"curveRadius":0.0},{"acceleration":-0.9726577713983157,"curvature":0,"pose":{"rotation":{"radians":0.0},"translation":{"x":3.354993152000002,"y":3.0}},"time":2.6317121345139585,"velocity":0.5242390101709442,"position":2.014556160000002,"holonomicRotation":95.03999999999994,"angularVelocity":0.0,"angularAcceleration":0.0,"curveRadius":0.0},{"acceleration":-0.9715875830601655,"curvature":0,"pose":{"rotation":{"radians":0.0},"translation":{"x":3.3638581760000017,"y":3.0}},"time":2.649188453070094,"velocity":0.507259236064199,"position":2.023421184000002,"holonomicRotation":94.67999999999994,"angularVelocity":0.0,"angularAcceleration":0.0,"curveRadius":0.0},{"acceleration":-0.9702921092922784,"curvature":0,"pose":{"rotation":{"radians":0.0},"translation":{"x":3.3729482240000017,"y":3.0}},"time":2.6677687335073386,"velocity":0.4892309365675029,"position":2.032511232000002,"holonomicRotation":94.31999999999994,"angularVelocity":0.0,"angularAcceleration":0.0,"curveRadius":0.0},{"acceleration":-0.9687145616746023,"curvature":0,"pose":{"rotation":{"radians":0.0},"translation":{"x":3.3822644480000017,"y":3.0}},"time":2.68758919776906,"velocity":0.4700305642180225,"position":2.041827456000002,"holonomicRotation":93.95999999999994,"angularVelocity":0.0,"angularAcceleration":0.0,"curveRadius":0.0},{"acceleration":-0.9667754660505647,"curvature":0,"pose":{"rotation":{"radians":0.0},"translation":{"x":3.391808000000002,"y":3.0}},"time":2.70882045958903,"velocity":0.44950470117717906,"position":2.051371008000002,"holonomicRotation":93.59999999999994,"angularVelocity":0.0,"angularAcceleration":0.0,"curveRadius":0.0},{"acceleration":-0.9643602954189332,"curvature":0,"pose":{"rotation":{"radians":0.0},"translation":{"x":3.4015800320000023,"y":3.0}},"time":2.731681223126981,"velocity":0.4274586884982185,"position":2.0611430400000024,"holonomicRotation":93.23999999999994,"angularVelocity":0.0,"angularAcceleration":0.0,"curveRadius":0.0},{"acceleration":-0.96129795477441,"curvature":0,"pose":{"rotation":{"radians":0.0},"translation":{"x":3.411581696000002,"y":3.0}},"time":2.7564599624443207,"velocity":0.4036389370705715,"position":2.071144704000002,"holonomicRotation":92.87999999999994,"angularVelocity":0.0,"angularAcceleration":0.0,"curveRadius":0.0},{"acceleration":-0.9573210800727301,"curvature":0,"pose":{"rotation":{"radians":0.0},"translation":{"x":3.4218141440000016,"y":3.0}},"time":2.783551146731515,"velocity":0.37770397526830524,"position":2.0813771520000017,"holonomicRotation":92.51999999999994,"angularVelocity":0.0,"angularAcceleration":0.0,"curveRadius":0.0},{"acceleration":-0.9519871568388133,"curvature":0,"pose":{"rotation":{"radians":0.0},"translation":{"x":3.432278528000002,"y":3.0}},"time":2.8135201224836965,"velocity":0.34917389524861464,"position":2.091841536000002,"holonomicRotation":92.15999999999993,"angularVelocity":0.0,"angularAcceleration":0.0,"curveRadius":0.0},{"acceleration":-0.9445059879786372,"curvature":0,"pose":{"rotation":{"radians":0.0},"translation":{"x":3.4429760000000025,"y":3.0}},"time":2.84723055222218,"velocity":0.31733419250328376,"position":2.1025390080000026,"holonomicRotation":91.79999999999993,"angularVelocity":0.0,"angularAcceleration":0.0,"curveRadius":0.0},{"acceleration":-0.9333094357615496,"curvature":0,"pose":{"rotation":{"radians":0.0},"translation":{"x":3.453907712000002,"y":3.0}},"time":2.886129347120603,"velocity":0.2810295801848326,"position":2.1134707200000022,"holonomicRotation":91.43999999999993,"angularVelocity":0.0,"angularAcceleration":0.0,"curveRadius":0.0},{"acceleration":-0.9147488012423666,"curvature":0,"pose":{"rotation":{"radians":0.0},"translation":{"x":3.4650748160000022,"y":3.0}},"time":2.933023750168792,"velocity":0.2381329812115253,"position":2.1246378240000023,"holonomicRotation":91.07999999999993,"angularVelocity":0.0,"angularAcceleration":0.0,"curveRadius":0.0},{"acceleration":-0.877577019448791,"curvature":0,"pose":{"rotation":{"radians":0.0},"translation":{"x":3.476478464000002,"y":3.0}},"time":2.995122872510306,"velocity":0.18363621851667347,"position":2.1360414720000023,"holonomicRotation":90.71999999999993,"angularVelocity":0.0,"angularAcceleration":0.0,"curveRadius":0.0},{"acceleration":-0.7034880487641015,"curvature":0,"pose":{"rotation":{"radians":0.0},"translation":{"x":3.488119808000002,"y":3.0}},"time":3.1477095298562223,"velocity":0.07629332867295828,"position":2.1476828160000023,"holonomicRotation":90.35999999999993,"angularVelocity":0.0,"angularAcceleration":0.0,"curveRadius":0.0}]